mET_weap/Classification.py
mET_weap/DEM_1km.py
mET_weap/Kc_Fc.py
mET_weap/__init__.py
mET_weap/download_ERA5_cds.py
mET_weap/download_geopotential_cdsapi.py
mET_weap/ecmwf_daily.py
mET_weap/get_modis.py
mET_weap/hdf2tif.py
mET_weap/modis_process.py
mET_weap/synthesize.py
mET_weap/utils.py
mET_weap/Tab_ndvi_kc_fc/NDVI-FC.xlsx
mET_weap/Tab_ndvi_kc_fc/ndvi_kckcb.xlsx
mET_weap/mET_weap_doc/mET_weap_doc.pdf
mET_weap/mET_weap_test/userconfig.py
mET_weap/mET_weap_test/usermain.py
mET_weap/mET_weap_test/Gtopo30/README.md
mET_weap/mET_weap_test/Tab_ndvi_kc_fc/NDVI-FC.xlsx
mET_weap/mET_weap_test/Tab_ndvi_kc_fc/ndvi_kckcb.xlsx
mET_weap/mET_weap_test/zonage/Atlas_Piemont_Haouz.cpg
mET_weap/mET_weap_test/zonage/Atlas_Piemont_Haouz.dbf
mET_weap/mET_weap_test/zonage/Atlas_Piemont_Haouz.prj
mET_weap/mET_weap_test/zonage/Atlas_Piemont_Haouz.sbn
mET_weap/mET_weap_test/zonage/Atlas_Piemont_Haouz.sbx
mET_weap/mET_weap_test/zonage/Atlas_Piemont_Haouz.shp
mET_weap/mET_weap_test/zonage/Atlas_Piemont_Haouz.shp.xml
mET_weap/mET_weap_test/zonage/Atlas_Piemont_Haouz.shx
mET_weap-1.3.dist-info/METADATA
mET_weap-1.3.dist-info/RECORD
mET_weap-1.3.dist-info/WHEEL
mET_weap-1.3.dist-info/top_level.txt
