Metadata-Version: 2.1
Name: mET-weap
Version: 1.3
Summary: ERA5/MODIS Preprocessor for WEAP 21
Home-page: UNKNOWN
Author: Michel Le Page, Cindy Gosset, Antoine Beaumont, CESBIO
Author-email: michel.lepage@cesbio.cnes.fr
License: UNKNOWN
Platform: UNKNOWN
Classifier: Development Status :: 3 - Alpha
Classifier: Intended Audience :: End Users/Desktop
Classifier: Topic :: Software Development :: Build Tools
Classifier: License :: OSI Approved :: GNU General Public License v3 (GPLv3)
Classifier: Programming Language :: Python :: 3
Requires-Dist: numpy (>="1.11.3")
Requires-Dist: pillow (>="3.4.2")
Requires-Dist: xlrd (>="1.0.0")
Requires-Dist: scipy (>="0.19.1")
Requires-Dist: ecmwf-api-client (>="1.4.2")
Requires-Dist: requests (>="2.14.2")
Requires-Dist: python-dateutil (>="2.4")
Requires-Dist: cdsapi (>="0.1.1")
Requires-Dist: netCDF4 (>="1.4.1")
